README.md
setup.py
limp/__init__.py
limp/environment.py
limp/errors.py
limp/evaluation.py
limp/syntax.py
limp/syntax_tree.py
limp/tokens.py
limp.egg-info/PKG-INFO
limp.egg-info/SOURCES.txt
limp.egg-info/dependency_links.txt
limp.egg-info/entry_points.txt
limp.egg-info/requires.txt
limp.egg-info/top_level.txt
limp/evaluators/__init__.py
limp/parsing/__init__.py
limp/parsing/conditional.py
limp/parsing/function.py
limp/parsing/function_call.py
limp/parsing/list_.py
limp/parsing/object_.py
limp/parsing/shared.py
limp/parsing/simple.py
limp/standard_library/__init__.py
limp/standard_library/booleans.py
limp/standard_library/comparisons.py
limp/standard_library/conditions.py
limp/standard_library/conversions.py
limp/standard_library/easter_eggs.py
limp/standard_library/functional.py
limp/standard_library/lists.py
limp/standard_library/loops.py
limp/standard_library/math.py
limp/standard_library/meta.py
limp/standard_library/objects.py
limp/standard_library/shared.py
limp/standard_library/strings.py
meta/__init__.py