Metadata-Version: 1.0
Name: limp
Version: 0.13
Summary: A general purpose programming language
Home-page: https://www.github.com/byxor/limp
Author: Brandon Ibbotson
Author-email: UNKNOWN
License: GPLv3
Platform: UNKNOWN
